bs_audit/__init__.py
bs_audit/__main__.py
bs_audit/audit.py
bs_audit/audit_async.py
bs_audit/base_audit.py
bs_audit/table_watch.py
bs_audit/table_watch_async.py
bs_audit/db/__init__.py
bs_audit/db/dao/postgresql/__init__.py
bs_audit/db/dao/postgresql/aud.py
bs_audit/db/dao/postgresql/aud_insert.py
bs_audit/db/dao/postgresql/aud_search.py
bs_audit/db/dao/postgresql/aud_select_one.py
bs_audit/db/dao/postgresql/cfg.py
bs_audit/db/dao/postgresql/cfg_changed_since.py
bs_audit/db/dao/postgresql/cfg_insert.py
bs_audit/db/dao/postgresql/cfg_select_one.py
bs_audit/db/dao/postgresql/cfg_upd_last_change.py
bs_audit/db/dao/postgresql/col.py
bs_audit/db/dao/postgresql/col_insert.py
bs_audit/db/dao/postgresql/tran.py
bs_audit/db/dao/postgresql/tran_insert.py
bs_audit/db/dao/postgresql/tran_select_one.py
bs_audit/db/dao_async/__init__.py
bs_audit/db/dao_async/postgresql/__init__.py
bs_audit/db/dao_async/postgresql/aud.py
bs_audit/db/dao_async/postgresql/aud_insert.py
bs_audit/db/dao_async/postgresql/aud_search.py
bs_audit/db/dao_async/postgresql/aud_select_one.py
bs_audit/db/dao_async/postgresql/cfg.py
bs_audit/db/dao_async/postgresql/cfg_changed_since.py
bs_audit/db/dao_async/postgresql/cfg_insert.py
bs_audit/db/dao_async/postgresql/cfg_select_one.py
bs_audit/db/dao_async/postgresql/cfg_upd_last_change.py
bs_audit/db/dao_async/postgresql/col.py
bs_audit/db/dao_async/postgresql/col_insert.py
bs_audit/db/dao_async/postgresql/tran.py
bs_audit/db/dao_async/postgresql/tran_insert.py
bs_audit/db/dao_async/postgresql/tran_select_one.py
bs_audit/db/tables/__init__.py
bs_audit/db/tables/aud.py
bs_audit/db/tables/aud_key.py
bs_audit/db/tables/cfg.py
bs_audit/db/tables/cfg_key.py
bs_audit/db/tables/col.py
bs_audit/db/tables/col_key.py
bs_audit/db/tables/iaud_search.py
bs_audit/db/tables/icfg_changed_since.py
bs_audit/db/tables/icfg_upd_last_change.py
bs_audit/db/tables/oaud_search.py
bs_audit/db/tables/ocfg_changed_since.py
bs_audit/db/tables/tran.py
bs_audit/db/tables/tran_key.py
bitsmiths_audit-2.2.2.dist-info/LICENCE
bitsmiths_audit-2.2.2.dist-info/METADATA
bitsmiths_audit-2.2.2.dist-info/WHEEL
bitsmiths_audit-2.2.2.dist-info/entry_points.txt
bitsmiths_audit-2.2.2.dist-info/top_level.txt
bitsmiths_audit-2.2.2.dist-info/RECORD
